{
	"h_prince" : {
		"army" : [
			{ "creature" : "goblin", "max" : 25, "min" : 20 },
			{ "creature" : "goblin", "max" : 25, "min" : 20 },
			{ "creature" : "goblinWolfRider", "max" : 15, "min" : 10 }
		],
		"class" : "knight",
		"images" : {
			"large" : "heroes/castle/prince_l.bmp",
			"small" : "heroes/castle/prince_s.bmp",
			"specialtyLarge" : "heroes/castle/prince_sl.bmp",
			"specialtySmall" : "heroes/castle/prince_ss.bmp"
		},
		"skills" : [
			{ "level" : "basic", "skill" : "leadership" },
			{ "level" : "basic", "skill" : "offence" }
		],
		"specialty" : {
			"creature" : "goblin"
		},
		"texts" : {
			"biography" : "",
			"name" : "Prince",
			"specialty" : {
				"description" : "{Goblin}\n",
				"name" : "Goblin",
				"tooltip" : ""
			}
		}
	}
}
